Workbook

Sheet Crop Reference Table
A1: AGRISURE — Crop Reference Table
A2: Source: NAERLS 2024 Report | FAO Nigeria | FMARD Estimates
A3: Crop | B3: Base Yield (t/ha) | C3: Input Cost (₦/ha) | D3: Market Price (₦/tonne) | E3: Source
A4: Maize | B4: 2.5 | C4: 561000 | D4: 120000 | E4: NAERLS 2024 Report
A5: Rice | B5: 1.9 | C5: 583000 | D5: 650000 | E5: NAERLS 2024 Report
A6: Cassava | B6: 7.8 | C6: 280000 | D6: 80000 | E6: FAO / FAOSTAT Nigeria
A7: Soybeans | B7: 1.2 | C7: 320000 | D7: 400000 | E7: FAO / FMARD Estimates
A9: 📘 Blue numbers = inputs you can update. These figures are real Nigerian averages.

Sheet Farmer Data
A1: AGRISURE — Farmer Sample Dataset (Input Data)
A2: Enter farmer details below — blue cells are inputs you fill in
A3: Farmer Name | B3: Crop | C3: Farm Size (ha) | D3: Actual Input Spend (₦) | E3: Loan Requested (₦) | F3: Season (months)
A4: Samuel Okonjo | B4: Maize | C4: 3 | D4: 400000 | E4: 500000 | F4: 4
A5: David Mwangi | B5: Maize | C5: 5 | D5: 700000 | E5: 900000 | F5: 4
A6: Sarah Otieno | B6: Rice | C6: 2 | D6: 200000 | E6: 300000 | F6: 5
A7: Emmanuel Kibet | B7: Cassava | C7: 4 | D7: 350000 | E7: 600000 | F7: 9
A8: Linah Chemutai | B8: Soybeans | C8: 1 | D8: 150000 | E8: 200000 | F8: 4
A9: Ahmed Ali | B9: Maize | C9: 8 | D9: 1200000 | E9: 1500000 | F9: 4
A10: Beatrice Kimani | B10: Rice | C10: 6 | D10: 900000 | E10: 700000 | F10: 5
A11: Samuel Mwangi | B11: Cassava | C11: 2 | D11: 200000 | E11: 400000 | F11: 9
A12: James Wilson | B12: Soybeans | C12: 10 | D12: 1200000 | E12: 2000000 | F12: 4
A13: Jane Doe | B13: Rice | C13: 3 | D13: 400000 | E13: 350000 | F13: 5
A14: Amara Diallo | B14: Cassava | C14: 7 | D14: 560000 | E14: 800000 | F14: 9
A15: Kofi Mensah | B15: Maize | C15: 2 | D15: 250000 | E15: 300000 | F15: 4
... A18: Chidi Okafor | B18: Cassava | C18: 9 | D18: 1100000 | E18: 1200000 | F18: 9
A20: 📘 Blue = inputs you fill. Crop must exactly match: Maize | Rice | Cassava | Soybeans

Sheet Calculations
A2: Formulas pull data from 'Farmer Data' and 'Crop Reference Table' sheets automatically
A3: 🟢 Green = linked from other sheets | ⚫ Black = calculated formula
A4: Farmer Name | B4: Input Efficiency | C4: Predicted Yield (t) | D4: Projected Revenue (₦) | E4: Risk Score | F4: Loan Decision
A5: ='Farmer Data'!A4 -> Samuel Okonjo | B5: =IFERROR('Farmer Data'!D4/(VLOOKUP('Farmer Data'!B4,'Crop Reference Table'!A:C,3,0)*'Farmer Data'!C4),0) -> 0.23767083 | C5: =IFERROR('Farmer Data'!C4*VLOOKUP('Farmer Data'!B4,'Crop Reference Table'!A:B,2,0)*MIN(B5,1),0) -> 1.7825312 | D5: =IFERROR(C5*VLOOKUP('Farmer Data'!B4,'Crop Reference Table'!A:D,4,0),0) -> 213903.74 | E5: =IFERROR('Farmer Data'!E4/D5,0) -> 2.3375 | F5: =IFERROR(IF(E5<0.5,"✅ Approve",IF(E5<=0.75,"🟡 Conditional","❌ Reject")),"N/A") -> ❌ Reject
A6: ='Farmer Data'!A5 -> David Mwangi | B6: =IFERROR('Farmer Data'!D5/(VLOOKUP('Farmer Data'!B5,'Crop Reference Table'!A:C,3,0)*'Farmer Data'!C5),0) -> 0.24955437 | C6: =IFERROR('Farmer Data'!C5*VLOOKUP('Farmer Data'!B5,'Crop Reference Table'!A:B,2,0)*MIN(B6,1),0) -> 3.1194296 | D6: =IFERROR(C6*VLOOKUP('Farmer Data'!B5,'Crop Reference Table'!A:D,4,0),0) -> 374331.55 | E6: =IFERROR('Farmer Data'!E5/D6,0) -> 2.4042857 | F6: =IFERROR(IF(E6<0.5,"✅ Approve",IF(E6<=0.75,"🟡 Conditional","❌ Reject")),"N/A") -> ❌ Reject
A7: ='Farmer Data'!A6 -> Sarah Otieno | B7: =IFERROR('Farmer Data'!D6/(VLOOKUP('Farmer Data'!B6,'Crop Reference Table'!A:C,3,0)*'Farmer Data'!C6),0) -> 0.17152659 | C7: =IFERROR('Farmer Data'!C6*VLOOKUP('Farmer Data'!B6,'Crop Reference Table'!A:B,2,0)*MIN(B7,1),0) -> 0.65180103 | D7: =IFERROR(C7*VLOOKUP('Farmer Data'!B6,'Crop Reference Table'!A:D,4,0),0) -> 423670.67 | E7: =IFERROR('Farmer Data'!E6/D7,0) -> 0.70809717 | F7: =IFERROR(IF(E7<0.5,"✅ Approve",IF(E7<=0.75,"🟡 Conditional","❌ Reject")),"N/A") -> 🟡 Conditional
A8: ='Farmer Data'!A7 -> Emmanuel Kibet | B8: =IFERROR('Farmer Data'!D7/(VLOOKUP('Farmer Data'!B7,'Crop Reference Table'!A:C,3,0)*'Farmer Data'!C7),0) -> 0.3125 | C8: =IFERROR('Farmer Data'!C7*VLOOKUP('Farmer Data'!B7,'Crop Reference Table'!A:B,2,0)*MIN(B8,1),0) -> 9.75 | D8: =IFERROR(C8*VLOOKUP('Farmer Data'!B7,'Crop Reference Table'!A:D,4,0),0) -> 780000 | E8: =IFERROR('Farmer Data'!E7/D8,0) -> 0.76923077 | F8: =IFERROR(IF(E8<0.5,"✅ Approve",IF(E8<=0.75,"🟡 Conditional","❌ Reject")),"N/A") -> ❌ Reject
A9: ='Farmer Data'!A8 -> Linah Chemutai | B9: =IFERROR('Farmer Data'!D8/(VLOOKUP('Farmer Data'!B8,'Crop Reference Table'!A:C,3,0)*'Farmer Data'!C8),0) -> 0.46875 | C9: =IFERROR('Farmer Data'!C8*VLOOKUP('Farmer Data'!B8,'Crop Reference Table'!A:B,2,0)*MIN(B9,1),0) -> 0.5625 | D9: =IFERROR(C9*VLOOKUP('Farmer Data'!B8,'Crop Reference Table'!A:D,4,0),0) -> 225000 | E9: =IFERROR('Farmer Data'!E8/D9,0) -> 0.88888889 | F9: =IFERROR(IF(E9<0.5,"✅ Approve",IF(E9<=0.75,"🟡 Conditional","❌ Reject")),"N/A") -> ❌ Reject
A10: ='Farmer Data'!A9 -> Ahmed Ali | B10: =IFERROR('Farmer Data'!D9/(VLOOKUP('Farmer Data'!B9,'Crop Reference Table'!A:C,3,0)*'Farmer Data'!C9),0) -> 0.26737968 | C10: =IFERROR('Farmer Data'!C9*VLOOKUP('Farmer Data'!B9,'Crop Reference Table'!A:B,2,0)*MIN(B10,1),0) -> 5.3475936 | D10: =IFERROR(C10*VLOOKUP('Farmer Data'!B9,'Crop Reference Table'!A:D,4,0),0) -> 641711.23 | E10: =IFERROR('Farmer Data'!E9/D10,0) -> 2.3375 | F10: =IFERROR(IF(E10<0.5,"✅ Approve",IF(E10<=0.75,"🟡 Conditional","❌ Reject")),"N/A") -> ❌ Reject
A11: ='Farmer Data'!A10 -> Beatrice Kimani | B11: =IFERROR('Farmer Data'!D10/(VLOOKUP('Farmer Data'!B10,'Crop Reference Table'!A:C,3,0)*'Farmer Data'!C10),0) -> 0.25728988 | C11: =IFERROR('Farmer Data'!C10*VLOOKUP('Farmer Data'!B10,'Crop Reference Table'!A:B,2,0)*MIN(B11,1),0) -> 2.9331046 | D11: =IFERROR(C11*VLOOKUP('Farmer Data'!B10,'Crop Reference Table'!A:D,4,0),0) -> 1906518 | E11: =IFERROR('Farmer Data'!E10/D11,0) -> 0.36716149 | F11: =IFERROR(IF(E11<0.5,"✅ Approve",IF(E11<=0.75,"🟡 Conditional","❌ Reject")),"N/A") -> ✅ Approve
A12: ='Farmer Data'!A11 -> Samuel Mwangi | B12: =IFERROR('Farmer Data'!D11/(VLOOKUP('Farmer Data'!B11,'Crop Reference Table'!A:C,3,0)*'Farmer Data'!C11),0) -> 0.35714286 | C12: =IFERROR('Farmer Data'!C11*VLOOKUP('Farmer Data'!B11,'Crop Reference Table'!A:B,2,0)*MIN(B12,1),0) -> 5.5714286 | D12: =IFERROR(C12*VLOOKUP('Farmer Data'!B11,'Crop Reference Table'!A:D,4,0),0) -> 445714.29 | E12: =IFERROR('Farmer Data'!E11/D12,0) -> 0.8974359 | F12: =IFERROR(IF(E12<0.5,"✅ Approve",IF(E12<=0.75,"🟡 Conditional","❌ Reject")),"N/A") -> ❌ Reject
A13: ='Farmer Data'!A12 -> James Wilson | B13: =IFERROR('Farmer Data'!D12/(VLOOKUP('Farmer Data'!B12,'Crop Reference Table'!A:C,3,0)*'Farmer Data'!C12),0) -> 0.375 | C13: =IFERROR('Farmer Data'!C12*VLOOKUP('Farmer Data'!B12,'Crop Reference Table'!A:B,2,0)*MIN(B13,1),0) -> 4.5 | D13: =IFERROR(C13*VLOOKUP('Farmer Data'!B12,'Crop Reference Table'!A:D,4,0),0) -> 1800000 | E13: =IFERROR('Farmer Data'!E12/D13,0) -> 1.1111111 | F13: =IFERROR(IF(E13<0.5,"✅ Approve",IF(E13<=0.75,"🟡 Conditional","❌ Reject")),"N/A") -> ❌ Reject
A14: ='Farmer Data'!A13 -> Jane Doe | B14: =IFERROR('Farmer Data'!D13/(VLOOKUP('Farmer Data'!B13,'Crop Reference Table'!A:C,3,0)*'Farmer Data'!C13),0) -> 0.22870212 | C14: =IFERROR('Farmer Data'!C13*VLOOKUP('Farmer Data'!B13,'Crop Reference Table'!A:B,2,0)*MIN(B14,1),0) -> 1.3036021 | D14: =IFERROR(C14*VLOOKUP('Farmer Data'!B13,'Crop Reference Table'!A:D,4,0),0) -> 847341.34 | E14: =IFERROR('Farmer Data'!E13/D14,0) -> 0.41305668 | F14: =IFERROR(IF(E14<0.5,"✅ Approve",IF(E14<=0.75,"🟡 Conditional","❌ Reject")),"N/A") -> ✅ Approve
A15: ='Farmer Data'!A14 -> Amara Diallo | B15: =IFERROR('Farmer Data'!D14/(VLOOKUP('Farmer Data'!B14,'Crop Reference Table'!A:C,3,0)*'Farmer Data'!C14),0) -> 0.28571429 | C15: =IFERROR('Farmer Data'!C14*VLOOKUP('Farmer Data'!B14,'Crop Reference Table'!A:B,2,0)*MIN(B15,1),0) -> 15.6 | D15: =IFERROR(C15*VLOOKUP('Farmer Data'!B14,'Crop Reference Table'!A:D,4,0),0) -> 1248000 | E15: =IFERROR('Farmer Data'!E14/D15,0) -> 0.64102564 | F15: =IFERROR(IF(E15<0.5,"✅ Approve",IF(E15<=0.75,"🟡 Conditional","❌ Reject")),"N/A") -> 🟡 Conditional
A16: ='Farmer Data'!A15 -> Kofi Mensah | B16: =IFERROR('Farmer Data'!D15/(VLOOKUP('Farmer Data'!B15,'Crop Reference Table'!A:C,3,0)*'Farmer Data'!C15),0) -> 0.2228164 | C16: =IFERROR('Farmer Data'!C15*VLOOKUP('Farmer Data'!B15,'Crop Reference Table'!A:B,2,0)*MIN(B16,1),0) -> 1.114082 | D16: =IFERROR(C16*VLOOKUP('Farmer Data'!B15,'Crop Reference Table'!A:D,4,0),0) -> 133689.84 | E16: =IFERROR('Farmer Data'!E15/D16,0) -> 2.244 | F16: =IFERROR(IF(E16<0.5,"✅ Approve",IF(E16<=0.75,"🟡 Conditional","❌ Reject")),"N/A") -> ❌ Reject
... A19: ='Farmer Data'!A18 -> Chidi Okafor | B19: =IFERROR('Farmer Data'!D18/(VLOOKUP('Farmer Data'!B18,'Crop Reference Table'!A:C,3,0)*'Farmer Data'!C18),0) -> 0.43650794 | C19: =IFERROR('Farmer Data'!C18*VLOOKUP('Farmer Data'!B18,'Crop Reference Table'!A:B,2,0)*MIN(B19,1),0) -> 30.642857 | D19: =IFERROR(C19*VLOOKUP('Farmer Data'!B18,'Crop Reference Table'!A:D,4,0),0) -> 2451428.6 | E19: =IFERROR('Farmer Data'!E18/D19,0) -> 0.48951049 | F19: =IFERROR(IF(E19<0.5,"✅ Approve",IF(E19<=0.75,"🟡 Conditional","❌ Reject")),"N/A") -> ✅ Approve
A21: RISK THRESHOLD KEY
A22: Threshold: | B22: Risk Score < 0.50 | D22: ✅ Approve
A23: Threshold: | B23: Risk Score 0.50 – 0.75 | D23: 🟡 Conditional Approval
A24: Threshold: | B24: Risk Score > 0.75 | D24: ❌ Reject

Sheet Dashboard
A1: AGRISURE — Results Dashboard
A2: Summary of yield predictions and loan decisions across all 15 farmers
B5: =COUNTA(Calculations!A5:A19) -> 15 | D5: =COUNTIF(Calculations!F5:F19,"*Approve*") -> 4 | F5: =COUNTIF(Calculations!F5:F19,"*Conditional*") -> 2 | H5: =COUNTIF(Calculations!F5:F19,"*Reject*") -> 9
B6: Total Farmers | D6: ✅ Approved | F6: 🟡 Conditional | H6: ❌ Rejected
A9: Farmer | B9: Crop | C9: Farm Size (ha) | D9: Predicted Yield (t) | E9: Projected Revenue (₦) | F9: Risk Score | G9: Decision
A10: =Calculations!A5 -> Samuel Okonjo | B10: ='Farmer Data'!B4 -> Maize | C10: ='Farmer Data'!C4 -> 3 | D10: =Calculations!C5 -> 1.7825312 | E10: =Calculations!D5 -> 213903.74 | F10: =Calculations!E5 -> 2.3375 | G10: =Calculations!F5 -> ❌ Reject
A11: =Calculations!A6 -> David Mwangi | B11: ='Farmer Data'!B5 -> Maize | C11: ='Farmer Data'!C5 -> 5 | D11: =Calculations!C6 -> 3.1194296 | E11: =Calculations!D6 -> 374331.55 | F11: =Calculations!E6 -> 2.4042857 | G11: =Calculations!F6 -> ❌ Reject
A12: =Calculations!A7 -> Sarah Otieno | B12: ='Farmer Data'!B6 -> Rice | C12: ='Farmer Data'!C6 -> 2 | D12: =Calculations!C7 -> 0.65180103 | E12: =Calculations!D7 -> 423670.67 | F12: =Calculations!E7 -> 0.70809717 | G12: =Calculations!F7 -> 🟡 Conditional
A13: =Calculations!A8 -> Emmanuel Kibet | B13: ='Farmer Data'!B7 -> Cassava | C13: ='Farmer Data'!C7 -> 4 | D13: =Calculations!C8 -> 9.75 | E13: =Calculations!D8 -> 780000 | F13: =Calculations!E8 -> 0.76923077 | G13: =Calculations!F8 -> ❌ Reject
A14: =Calculations!A9 -> Linah Chemutai | B14: ='Farmer Data'!B8 -> Soybeans | C14: ='Farmer Data'!C8 -> 1 | D14: =Calculations!C9 -> 0.5625 | E14: =Calculations!D9 -> 225000 | F14: =Calculations!E9 -> 0.88888889 | G14: =Calculations!F9 -> ❌ Reject
A15: =Calculations!A10 -> Ahmed Ali | B15: ='Farmer Data'!B9 -> Maize | C15: ='Farmer Data'!C9 -> 8 | D15: =Calculations!C10 -> 5.3475936 | E15: =Calculations!D10 -> 641711.23 | F15: =Calculations!E10 -> 2.3375 | G15: =Calculations!F10 -> ❌ Reject
A16: =Calculations!A11 -> Beatrice Kimani | B16: ='Farmer Data'!B10 -> Rice | C16: ='Farmer Data'!C10 -> 6 | D16: =Calculations!C11 -> 2.9331046 | E16: =Calculations!D11 -> 1906518 | F16: =Calculations!E11 -> 0.36716149 | G16: =Calculations!F11 -> ✅ Approve
A17: =Calculations!A12 -> Samuel Mwangi | B17: ='Farmer Data'!B11 -> Cassava | C17: ='Farmer Data'!C11 -> 2 | D17: =Calculations!C12 -> 5.5714286 | E17: =Calculations!D12 -> 445714.29 | F17: =Calculations!E12 -> 0.8974359 | G17: =Calculations!F12 -> ❌ Reject
A18: =Calculations!A13 -> James Wilson | B18: ='Farmer Data'!B12 -> Soybeans | C18: ='Farmer Data'!C12 -> 10 | D18: =Calculations!C13 -> 4.5 | E18: =Calculations!D13 -> 1800000 | F18: =Calculations!E13 -> 1.1111111 | G18: =Calculations!F13 -> ❌ Reject
A19: =Calculations!A14 -> Jane Doe | B19: ='Farmer Data'!B13 -> Rice | C19: ='Farmer Data'!C13 -> 3 | D19: =Calculations!C14 -> 1.3036021 | E19: =Calculations!D14 -> 847341.34 | F19: =Calculations!E14 -> 0.41305668 | G19: =Calculations!F14 -> ✅ Approve
A20: =Calculations!A15 -> Amara Diallo | B20: ='Farmer Data'!B14 -> Cassava | C20: ='Farmer Data'!C14 -> 7 | D20: =Calculations!C15 -> 15.6 | E20: =Calculations!D15 -> 1248000 | F20: =Calculations!E15 -> 0.64102564 | G20: =Calculations!F15 -> 🟡 Conditional
A21: =Calculations!A16 -> Kofi Mensah | B21: ='Farmer Data'!B15 -> Maize | C21: ='Farmer Data'!C15 -> 2 | D21: =Calculations!C16 -> 1.114082 | E21: =Calculations!D16 -> 133689.84 | F21: =Calculations!E16 -> 2.244 | G21: =Calculations!F16 -> ❌ Reject
... A24: =Calculations!A19 -> Chidi Okafor | B24: ='Farmer Data'!B18 -> Cassava | C24: ='Farmer Data'!C18 -> 9 | D24: =Calculations!C19 -> 30.642857 | E24: =Calculations!D19 -> 2451428.6 | F24: =Calculations!E19 -> 0.48951049 | G24: =Calculations!F19 -> ✅ Approve
A26: 📊 Tip: Select columns D & E then Insert → Chart to create a visual yield vs revenue chart
