Workbook

Sheet Crop Reference Table
A1: AGRISURE — Crop Reference Table
A2: Crop | B2: Base Yield (t/ha) | C2: Input Cost (₦/ha) | D2: Market Price (₦/tonne)
A3: Maize | B3: 2.5 | C3: 561000 | D3: 120000
A4: Rice | B4: 1.9 | C4: 583000 | D4: 650000
A5: Cassava | B5: 7.8 | C5: 280000 | D5: 80000
A6: Soyabeans | B6: 1.2 | C6: 320000 | D6: 400000

Sheet Farmer Data
A1: AGRISURE — Farmer Sample Dataset (Input Data)
A2: Farmer Name | B2: Crop | C2: Farm Size (ha) | D2: Actual Input Spend (₦) | E2: Loan Requested (₦) | F2: Season (months)
A3: Samuel Mwangi | B3: Cassava | C3: 9 | D3: 1100000 | E3: 1200000 | F3: 9
A4: Ahmed Ali | B4: Maize | C4: 4 | D4: 650000 | E4: 800000 | F4: 4
A5: Beatrice Kimani | B5: Soyabeans | C5: 2 | D5: 300000 | E5: 500000 | F5: 4
A6: David Mwangi | B6: Maize | C6: 5 | D6: 700000 | E6: 600000 | F6: 4
A7: Sarah Otieno | B7: Rice | C7: 6 | D7: 800000 | E7: 500000 | F7: 5
A8: Emmanuel Kibet | B8: Maize | C8: 4 | D8: 600000 | E8: 200000 | F8: 4
A9: Linah Chemutai | B9: Rice | C9: 8 | D9: 1200000 | E9: 1000000 | F9: 4

Sheet Calculations
A1: AGRISURE — Yield Prediction & Loan Risk Calculations
A2: Farmer Name | B2: Input Efficiency | C2: Predicted Yield (t) | D2: Projected Revenue (₦) | E2: Risk Score | F2: Loan Decision
A3: ='Farmer Data'!A3 -> Samuel Mwangi | B3: =IFERROR('Farmer Data'!D3/(VLOOKUP('Farmer Data'!B3,'Crop Reference Table'!A:C,3,0)*'Farmer Data'!C3),0) -> 0.43650794 | C3: =IFERROR('Farmer Data'!C3*VLOOKUP('Farmer Data'!B3,'Crop Reference Table'!A:B,2,0)*MIN(B3,1),0) -> 30.642857 | D3: =IFERROR(C3*VLOOKUP('Farmer Data'!B3,'Crop Reference Table'!A:D,4,0),0) -> 2451428.6 | E3: =IFERROR('Farmer Data'!E3/D3,0) -> 0.48951049 | F3: =IFERROR(IF(E3<0.5,"✅ Approve",IF(E3<=0.75,"🟡 Conditional","❌ Reject")),"N/A") -> ✅ Approve
A4: ='Farmer Data'!A4 -> Ahmed Ali | B4: =IFERROR('Farmer Data'!D4/(VLOOKUP('Farmer Data'!B4,'Crop Reference Table'!A:C,3,0)*'Farmer Data'!C4),0) -> 0.28966132 | C4: =IFERROR('Farmer Data'!C4*VLOOKUP('Farmer Data'!B4,'Crop Reference Table'!A:B,2,0)*MIN(B4,1),0) -> 2.8966132 | D4: =IFERROR(C4*VLOOKUP('Farmer Data'!B4,'Crop Reference Table'!A:D,4,0),0) -> 347593.58 | E4: =IFERROR('Farmer Data'!E4/D4,0) -> 2.3015385 | F4: =IFERROR(IF(E4<0.5,"✅ Approve",IF(E4<=0.75,"🟡 Conditional","❌ Reject")),"N/A") -> ❌ Reject
A5: ='Farmer Data'!A5 -> Beatrice Kimani | B5: =IFERROR('Farmer Data'!D5/(VLOOKUP('Farmer Data'!B5,'Crop Reference Table'!A:C,3,0)*'Farmer Data'!C5),0) -> 0.46875 | C5: =IFERROR('Farmer Data'!C5*VLOOKUP('Farmer Data'!B5,'Crop Reference Table'!A:B,2,0)*MIN(B5,1),0) -> 1.125 | D5: =IFERROR(C5*VLOOKUP('Farmer Data'!B5,'Crop Reference Table'!A:D,4,0),0) -> 450000 | E5: =IFERROR('Farmer Data'!E5/D5,0) -> 1.1111111 | F5: =IFERROR(IF(E5<0.5,"✅ Approve",IF(E5<=0.75,"🟡 Conditional","❌ Reject")),"N/A") -> ❌ Reject
A6: ='Farmer Data'!A6 -> David Mwangi | B6: =IFERROR('Farmer Data'!D6/(VLOOKUP('Farmer Data'!B6,'Crop Reference Table'!A:C,3,0)*'Farmer Data'!C6),0) -> 0.24955437 | C6: =IFERROR('Farmer Data'!C6*VLOOKUP('Farmer Data'!B6,'Crop Reference Table'!A:B,2,0)*MIN(B6,1),0) -> 3.1194296 | D6: =IFERROR(C6*VLOOKUP('Farmer Data'!B6,'Crop Reference Table'!A:D,4,0),0) -> 374331.55 | E6: =IFERROR('Farmer Data'!E6/D6,0) -> 1.6028571 | F6: =IFERROR(IF(E6<0.5,"✅ Approve",IF(E6<=0.75,"🟡 Conditional","❌ Reject")),"N/A") -> ❌ Reject
A7: ='Farmer Data'!A7 -> Sarah Otieno | B7: =IFERROR('Farmer Data'!D7/(VLOOKUP('Farmer Data'!B7,'Crop Reference Table'!A:C,3,0)*'Farmer Data'!C7),0) -> 0.22870212 | C7: =IFERROR('Farmer Data'!C7*VLOOKUP('Farmer Data'!B7,'Crop Reference Table'!A:B,2,0)*MIN(B7,1),0) -> 2.6072041 | D7: =IFERROR(C7*VLOOKUP('Farmer Data'!B7,'Crop Reference Table'!A:D,4,0),0) -> 1694682.7 | E7: =IFERROR('Farmer Data'!E7/D7,0) -> 0.29504049 | F7: =IFERROR(IF(E7<0.5,"✅ Approve",IF(E7<=0.75,"🟡 Conditional","❌ Reject")),"N/A") -> ✅ Approve
A8: ='Farmer Data'!A8 -> Emmanuel Kibet | B8: =IFERROR('Farmer Data'!D8/(VLOOKUP('Farmer Data'!B8,'Crop Reference Table'!A:C,3,0)*'Farmer Data'!C8),0) -> 0.26737968 | C8: =IFERROR('Farmer Data'!C8*VLOOKUP('Farmer Data'!B8,'Crop Reference Table'!A:B,2,0)*MIN(B8,1),0) -> 2.6737968 | D8: =IFERROR(C8*VLOOKUP('Farmer Data'!B8,'Crop Reference Table'!A:D,4,0),0) -> 320855.61 | E8: =IFERROR('Farmer Data'!E8/D8,0) -> 0.62333333 | F8: =IFERROR(IF(E8<0.5,"✅ Approve",IF(E8<=0.75,"🟡 Conditional","❌ Reject")),"N/A") -> 🟡 Conditional
A9: ='Farmer Data'!A9 -> Linah Chemutai | B9: =IFERROR('Farmer Data'!D9/(VLOOKUP('Farmer Data'!B9,'Crop Reference Table'!A:C,3,0)*'Farmer Data'!C9),0) -> 0.25728988 | C9: =IFERROR('Farmer Data'!C9*VLOOKUP('Farmer Data'!B9,'Crop Reference Table'!A:B,2,0)*MIN(B9,1),0) -> 3.9108062 | D9: =IFERROR(C9*VLOOKUP('Farmer Data'!B9,'Crop Reference Table'!A:D,4,0),0) -> 2542024 | E9: =IFERROR('Farmer Data'!E9/D9,0) -> 0.39338731 | F9: =IFERROR(IF(E9<0.5,"✅ Approve",IF(E9<=0.75,"🟡 Conditional","❌ Reject")),"N/A") -> ✅ Approve
A10: ='Farmer Data'!A10
A11: RISK THRESHOLD KEY
A12: Threshold: | B12: Risk Score < 0.50 | D12: ✅ Approve
A13: Threshold: | B13: Risk Score 0.50 – 0.75 | D13: 🟡 Conditional Approval
A14: Threshold: | B14: Risk Score > 0.75 | D14: ❌ Reject

Sheet Dashboard
B1: AGRISURE — Results Dashboard
B2: Summary of yield predictions and loan decisions across all Farmers
B4: =COUNTA(Calculations!A3:A9) -> 7 | D4: =COUNTIF(Calculations!F3:F9, "*Approve*") -> 3 | F4: =COUNTIF(Calculations!F3:F9, "*Conditional*") -> 1 | H4: =COUNTIF(Calculations!F3:F9, "*Reject*") -> 3
B5: Total Farmers | D5: ✅ Approved | F5: 🟡 Conditional | H5: ❌ Rejected
B7: Farmer | C7: Crop | D7: Farm Size (ha) | E7: Predicted Yield (t) | F7: Projected Revenue (₦) | G7: Risk Score | H7: Decision
B8: ='Farmer Data'!A3 -> Samuel Mwangi | C8: ='Farmer Data'!B3 -> Cassava | D8: ='Farmer Data'!C3 -> 9 | E8: =Calculations!C3 -> 30.642857 | F8: =Calculations!D3 -> 2451428.6 | G8: =Calculations!E3 -> 0.48951049 | H8: =Calculations!F3 -> ✅ Approve
B9: ='Farmer Data'!A4 -> Ahmed Ali | C9: ='Farmer Data'!B4 -> Maize | D9: ='Farmer Data'!C4 -> 4 | E9: =Calculations!C4 -> 2.8966132 | F9: =Calculations!D4 -> 347593.58 | G9: =Calculations!E4 -> 2.3015385 | H9: =Calculations!F4 -> ❌ Reject
B10: ='Farmer Data'!A5 -> Beatrice Kimani | C10: ='Farmer Data'!B5 -> Soyabeans | D10: ='Farmer Data'!C5 -> 2 | E10: =Calculations!C5 -> 1.125 | F10: =Calculations!D5 -> 450000 | G10: =Calculations!E5 -> 1.1111111 | H10: =Calculations!F5 -> ❌ Reject
B11: ='Farmer Data'!A6 -> David Mwangi | C11: ='Farmer Data'!B6 -> Maize | D11: ='Farmer Data'!C6 -> 5 | E11: =Calculations!C6 -> 3.1194296 | F11: =Calculations!D6 -> 374331.55 | G11: =Calculations!E6 -> 1.6028571 | H11: =Calculations!F6 -> ❌ Reject
B12: ='Farmer Data'!A7 -> Sarah Otieno | C12: ='Farmer Data'!B7 -> Rice | D12: ='Farmer Data'!C7 -> 6 | E12: =Calculations!C7 -> 2.6072041 | F12: =Calculations!D7 -> 1694682.7 | G12: =Calculations!E7 -> 0.29504049 | H12: =Calculations!F7 -> ✅ Approve
B13: ='Farmer Data'!A8 -> Emmanuel Kibet | C13: ='Farmer Data'!B8 -> Maize | D13: ='Farmer Data'!C8 -> 4 | E13: =Calculations!C8 -> 2.6737968 | F13: =Calculations!D8 -> 320855.61 | G13: =Calculations!E8 -> 0.62333333 | H13: =Calculations!F8 -> 🟡 Conditional
B14: ='Farmer Data'!A9 -> Linah Chemutai | C14: ='Farmer Data'!B9 -> Rice | D14: ='Farmer Data'!C9 -> 8 | E14: =Calculations!C9 -> 3.9108062 | F14: =Calculations!D9 -> 2542024 | G14: =Calculations!E9 -> 0.39338731 | H14: =Calculations!F9 -> ✅ Approve
